yujian/api.py
yujian/http.py
yujian-0.8.4.dist-info/LICENSE
yujian-0.8.4.dist-info/METADATA
yujian-0.8.4.dist-info/WHEEL
yujian-0.8.4.dist-info/top_level.txt
yujian-0.8.4.dist-info/RECORD
