Metadata-Version: 2.1
Name: yujian
Version: 0.8.4
Summary: The aio rabbitmq HTTP API client.
Author-email: Li zhigang <imlzg@126.com>
License: MIT License
Project-URL: Homepage, https://github.com/liangshanpo/yujian
Project-URL: Bug Tracker, https://github.com/liangshanpo/yujian/issues
Keywords: asyncio,rabbitmq,http,api,client,management
Classifier: Development Status :: 5 - Production/Stable
Classifier: Intended Audience :: Developers
Classifier: Topic :: Communications
Classifier: Topic :: Internet :: WWW/HTTP
Classifier: Topic :: Software Development :: Libraries :: Python Modules
Classifier: License :: OSI Approved :: MIT License
Classifier: Framework :: AsyncIO
Classifier: Operating System :: OS Independent
Classifier: Programming Language :: Python
Classifier: Programming Language :: Python :: 3 :: Only
Classifier: Programming Language :: Python :: 3.10
Classifier: Programming Language :: Python :: 3.11
Requires-Python: >=3.10
License-File: LICENSE
Requires-Dist: aiohttp[speedups]
Requires-Dist: loguru
